synadm/__init__.py
synadm/__main__.py
synadm/api.py
synadm/cli/__init__.py
synadm/cli/_common.py
synadm/cli/_helper.py
synadm/cli/group.py
synadm/cli/history.py
synadm/cli/matrix.py
synadm/cli/media.py
synadm/cli/notice.py
synadm/cli/raw.py
synadm/cli/regtok.py
synadm/cli/room.py
synadm/cli/user.py
synadm-0.49.2.dist-info/licenses/LICENSE
synadm-0.49.2.dist-info/METADATA
synadm-0.49.2.dist-info/WHEEL
synadm-0.49.2.dist-info/entry_points.txt
synadm-0.49.2.dist-info/top_level.txt
synadm-0.49.2.dist-info/RECORD
