Metadata-Version: 2.4
Name: synadm
Version: 0.49.2
Summary: Command line admin tool for Synapse (Matrix reference homeserver)
Home-page: https://codeberg.org/synadm/synadm
Author: Johannes Tiefenbacher
Author-email: jt@peek-a-boo.at
License: GPLv3+
Project-URL: Bug Tracker, https://codeberg.org/synadm/synadm/issues
Project-URL: Documentation, https://synadm.readthedocs.io/
Project-URL: Source Code, https://codeberg.org/synadm/synadm
Classifier: License :: OSI Approved :: GNU General Public License v3 or later (GPLv3+)
Classifier: Programming Language :: Python :: 3
Classifier: Programming Language :: Python :: 3.6
Classifier: Programming Language :: Python :: 3.7
Classifier: Programming Language :: Python :: 3.8
Classifier: Programming Language :: Python :: 3.9
Classifier: Programming Language :: Python :: 3.10
Classifier: Operating System :: OS Independent
Classifier: Topic :: System :: Systems Administration
Classifier: Topic :: Communications :: Chat
Classifier: Environment :: Console
License-File: LICENSE
Requires-Dist: Click<9.0,>=7.1
Requires-Dist: requests
Requires-Dist: requests-unixsocket
Requires-Dist: tabulate
Requires-Dist: PyYaml
Requires-Dist: click-option-group>=0.5.2
Requires-Dist: dnspython
Provides-Extra: scrape-docs
Requires-Dist: beautifulsoup4; extra == "scrape-docs"
Dynamic: author
Dynamic: author-email
Dynamic: classifier
Dynamic: description
Dynamic: description-content-type
Dynamic: home-page
Dynamic: license
Dynamic: license-file
Dynamic: project-url
Dynamic: provides-extra
Dynamic: requires-dist
Dynamic: summary
